{
  "main": {
    "id": "cc504055b3771da0",
    "type": "split",
    "children": [
      {
        "id": "adb17af9246bda0c",
        "type": "tabs",
        "children": [
          {
            "id": "63bf3093fd4328c9",
            "type": "leaf",
            "state": {
              "type": "markdown",
              "state": {
                "file": "minio 临时.md",
                "mode": "source",
                "source": false
              },
              "icon": "lucide-file",
              "title": "minio 临时"
            }
          },
          {
            "id": "a73221b113417bef",
            "type": "leaf",
            "state": {
              "type": "markdown",
              "state": {
                "file": "source/_posts/笔记：Minio 基础.md",
                "mode": "source",
                "source": false
              },
              "icon": "lucide-file",
              "title": "笔记：Minio 基础"
            }
          },
          {
            "id": "bc794127839b1a4b",
            "type": "leaf",
            "state": {
              "type": "markdown",
              "state": {
                "file": "source/_posts/笔记：Spring 整合 Minio.md",
                "mode": "source",
                "source": false
              },
              "icon": "lucide-file",
              "title": "笔记：Spring 整合 Minio"
            }
          },
          {
            "id": "9d7e56788ebaf1c8",
            "type": "leaf",
            "state": {
              "type": "markdown",
              "state": {
                "file": "source/_posts/笔记：搭建 Minio 环境.md",
                "mode": "source",
                "source": false
              },
              "icon": "lucide-file",
              "title": "笔记：搭建 Minio 环境"
            }
          },
          {
            "id": "b01b2773c946cda2",
            "type": "leaf",
            "state": {
              "type": "markdown",
              "state": {
                "file": "source/_posts/笔记：Minio 工具.md",
                "mode": "source",
                "source": false
              },
              "icon": "lucide-file",
              "title": "笔记：Minio 工具"
            }
          },
          {
            "id": "bbff8bacb0ffc315",
            "type": "leaf",
            "state": {
              "type": "markdown",
              "state": {
                "file": "templates/临时：es.md",
                "mode": "source",
                "source": false
              },
              "icon": "lucide-file",
              "title": "临时：es"
            }
          }
        ],
        "currentTab": 1
      }
    ],
    "direction": "vertical"
  },
  "left": {
    "id": "cc0268435ccef476",
    "type": "split",
    "children": [
      {
        "id": "d389120d82676c7b",
        "type": "tabs",
        "children": [
          {
            "id": "88017f6098597ebd",
            "type": "leaf",
            "state": {
              "type": "file-explorer",
              "state": {
                "sortOrder": "alphabetical",
                "autoReveal": false
              },
              "icon": "lucide-folder-closed",
              "title": "文件列表"
            }
          },
          {
            "id": "e6c49f1ef696d3a2",
            "type": "leaf",
            "state": {
              "type": "search",
              "state": {
                "query": "file: 笔记：Java",
                "matchingCase": false,
                "explainSearch": false,
                "collapseAll": false,
                "extraContext": false,
                "sortOrder": "alphabeticalReverse"
              },
              "icon": "lucide-search",
              "title": "搜索"
            }
          },
          {
            "id": "32a053845ab374ef",
            "type": "leaf",
            "state": {
              "type": "bookmarks",
              "state": {},
              "icon": "lucide-bookmark",
              "title": "书签"
            }
          },
          {
            "id": "f0f50224b84c45d6",
            "type": "leaf",
            "state": {
              "type": "kanban",
              "state": {
                "file": "Todo 看板.md",
                "kanbanViewState": {
                  "kanban-plugin": "board",
                  "list-collapse": [
                    false,
                    false
                  ]
                }
              },
              "icon": "lucide-trello",
              "title": "Todo 看板"
            }
          }
        ]
      }
    ],
    "direction": "horizontal",
    "width": 313.5041847229004,
    "collapsed": true
  },
  "right": {
    "id": "0803248b5c8c75de",
    "type": "split",
    "children": [
      {
        "id": "dd0e7d522924828a",
        "type": "tabs",
        "dimension": 35.91370558375635,
        "children": [
          {
            "id": "75fee5262daf945e",
            "type": "leaf",
            "state": {
              "type": "calendar",
              "state": {},
              "icon": "calendar-with-checkmark",
              "title": "Calendar"
            }
          },
          {
            "id": "57c1454a1beacf3d",
            "type": "leaf",
            "state": {
              "type": "git-view",
              "state": {},
              "icon": "git-pull-request",
              "title": "Source Control"
            }
          },
          {
            "id": "16f111340248c234",
            "type": "leaf",
            "state": {
              "type": "backlink",
              "state": {
                "file": "source/_posts/笔记：Hexo + Obsidian +Git Page.md",
                "collapseAll": false,
                "extraContext": false,
                "sortOrder": "alphabetical",
                "showSearch": false,
                "searchQuery": "",
                "backlinkCollapsed": false,
                "unlinkedCollapsed": true
              },
              "icon": "links-coming-in",
              "title": "笔记：Hexo + Obsidian +Git Page 的反向链接列表"
            }
          },
          {
            "id": "281f484723c72ac6",
            "type": "leaf",
            "state": {
              "type": "outline",
              "state": {
                "file": "source/_posts/笔记：Spring IOC.md",
                "followCursor": false,
                "showSearch": false,
                "searchQuery": ""
              },
              "icon": "lucide-list",
              "title": "笔记：Spring IOC 的大纲"
            }
          },
          {
            "id": "5e191d9dda043800",
            "type": "leaf",
            "state": {
              "type": "tag",
              "state": {
                "sortOrder": "frequency",
                "useHierarchy": true,
                "showSearch": false,
                "searchQuery": ""
              },
              "icon": "lucide-tags",
              "title": "标签"
            }
          },
          {
            "id": "9460cc407aeeaaef",
            "type": "leaf",
            "state": {
              "type": "outgoing-link",
              "state": {
                "file": "source/_posts/笔记：Minio 基础.md",
                "linksCollapsed": false,
                "unlinkedCollapsed": true
              },
              "icon": "links-going-out",
              "title": "笔记：Minio 基础 的出链列表"
            }
          }
        ]
      },
      {
        "id": "f7e55608ee89a0dd",
        "type": "tabs",
        "dimension": 64.08629441624365,
        "children": [
          {
            "id": "fbdd42d532677ed8",
            "type": "leaf",
            "state": {
              "type": "quiet-outline",
              "state": {},
              "icon": "lines-of-text",
              "title": "Quiet Outline"
            }
          },
          {
            "id": "cd6a8ca51af1d363",
            "type": "leaf",
            "state": {
              "type": "recent-files",
              "state": {},
              "icon": "clock",
              "title": "Recent Files"
            }
          },
          {
            "id": "c62f6bf0843d9bbe",
            "type": "leaf",
            "state": {
              "type": "kanban",
              "state": {
                "file": "Todo 看板.md",
                "kanbanViewState": {
                  "kanban-plugin": "board",
                  "list-collapse": [
                    false,
                    false
                  ]
                }
              },
              "icon": "lucide-trello",
              "title": "Todo 看板"
            }
          }
        ]
      }
    ],
    "direction": "horizontal",
    "width": 307.5
  },
  "left-ribbon": {
    "hiddenItems": {
      "daily-notes:打开/创建今天的日记": true,
      "obsidian-git:Open Git source control": false,
      "switcher:打开快速切换": true,
      "graph:查看关系图谱": false,
      "canvas:新建白板": false,
      "templates:插入模板": false,
      "command-palette:打开命令面板": false,
      "obsidian-excalidraw-plugin:新建绘图文件": false,
      "obsidian-kanban:创建新看板": false,
      "task-status:Change Checkbox Status": false,
      "omnisearch:Omnisearch": false
    }
  },
  "active": "a73221b113417bef",
  "lastOpenFiles": [
    "source/_posts/笔记：搭建 Minio 环境.md",
    "source/_posts/笔记：Spring 整合 Minio.md",
    "source/_posts/笔记：Minio 基础.md",
    "source/_posts/笔记：Minio 工具.md",
    "templates/临时：es.md",
    "source/_posts/笔记：MySQL 基础.md",
    "source/_posts/笔记：Minio 工具/image-20250714170717756.png",
    "source/_posts/笔记：Minio 工具",
    "minio 临时.md",
    "source/_posts/未命名看板.md",
    "templates/临时：mybatis.md",
    "source/_posts/笔记：Spring Authorization Server.md",
    "templates/mysql 临时.md",
    "Categories.md",
    "使用 Spring OAuth2 Authorization Server 开发授权服务器详细完整流.md",
    "templates/临时：mybatis/image-20250714161254838.png",
    "source/_posts/笔记：Spring Security.md",
    "templates/临时：OAUth.md",
    "templates/临时：mybatis/image-20250714142401540.png",
    "templates/临时：mybatis/image-20250714142356095.png",
    "templates/临时：mybatis/image-20250714142338238.png",
    "templates/临时：mybatis/image-20250714111238419.png",
    "templates/临时：mybatis/image-20250714103343673.png",
    "templates/临时：mybatis/image-20250714103337217.png",
    "templates/临时：mybatis/image-20250714094045430.png",
    "Todo 看板.md",
    "source/_posts/笔记：Spring Authorization Server/image-20250713165050243.png",
    "Edraw/Spring Authorization Server --- 客户端应用相关 MySQL 表 --- ER 图.eddx.zCdzDX",
    "Edraw/Spring Authorization Server --- 客户端应用相关 MySQL 表 --- ER 图.eddx.ghpIGZ",
    "Edraw/Spring Authorization Server --- 客户端应用相关 MySQL 表 --- ER 图.eddx.LJSHkK",
    "Edraw/Spring Authorization Server --- 客户端应用相关 MySQL 表 --- ER 图.eddx.yELxfp",
    "Edraw/Spring Authorization Server --- 客户端应用相关 MySQL 表 --- ER 图.eddx.wUoAWG",
    "Edraw/Spring Authorization Server --- 客户端应用相关 MySQL 表 --- ER 图.eddx.idGHvv",
    "Edraw/Spring Authorization Server --- 客户端应用相关 MySQL 表 --- ER 图.eddx.mFzQCD",
    "Edraw/Spring Authorization Server --- 客户端应用相关 MySQL 表 --- ER 图.eddx.ykMnOR",
    "Edraw/Spring Authorization Server --- 客户端应用相关 MySQL 表 --- ER 图.eddx.qDnFPq",
    "source/_posts/笔记：Java 数据类型.md",
    "source/_posts/笔记：Windows.md",
    "source/_posts/笔记：分布式 ID.md",
    "source/_posts/笔记：OAuth 协议.md",
    "source/_posts/笔记：Spring Boot.md",
    "source/_posts/笔记：奶块攻略.md",
    "临时：OAUth.md",
    "source/_posts/笔记：Java 项目创建和结构.md",
    "授权码模式（Authorization Code）+ PKCE（授权码交换的密钥证明）+ OIDC.md",
    "source/_posts/笔记：阿里云代码规约.md",
    "未命名.canvas",
    "Excalidraw/未命名.canvas"
  ]
}